{
  "version": "5",
  "dialect": "mysql",
  "id": "b73c8da0-5555-4d17-af80-77278269b982",
  "prevId": "e2bf9ed6-476b-419a-a83a-70c7930f3e67",
  "tables": {
    "RefreshToken": {
      "name": "RefreshToken",
      "columns": {
        "id": {
          "name": "id",
          "type": "varchar(36)",
          "primaryKey": false,
          "notNull": true,
          "autoincrement": false
        },
        "userId": {
          "name": "userId",
          "type": "varchar(36)",
          "primaryKey": false,
          "notNull": true,
          "autoincrement": false
        },
        "expiresAt": {
          "name": "expiresAt",
          "type": "datetime",
          "primaryKey": false,
          "notNull": true,
          "autoincrement": false
        },
        "createdAt": {
          "name": "createdAt",
          "type": "datetime",
          "primaryKey": false,
          "notNull": true,
          "autoincrement": false
        },
        "updatedAt": {
          "name": "updatedAt",
          "type": "datetime",
          "primaryKey": false,
          "notNull": false,
          "autoincrement": false,
          "default": null
        }
      },
      "indexes": {
        "expiresAt": {
          "name": "expiresAt",
          "columns": [
            "expiresAt"
          ],
          "isUnique": false
        }
      },
      "foreignKeys": {
        "RefreshToken_userId_User_id_fk": {
          "name": "RefreshToken_userId_User_id_fk",
          "tableFrom": "RefreshToken",
          "tableTo": "User",
          "columnsFrom": [
            "userId"
          ],
          "columnsTo": [
            "id"
          ],
          "onDelete": "cascade",
          "onUpdate": "no action"
        }
      },
      "compositePrimaryKeys": {
        "RefreshToken_id": {
          "name": "RefreshToken_id",
          "columns": [
            "id"
          ]
        }
      },
      "uniqueConstraints": {
        "userId": {
          "name": "userId",
          "columns": [
            "userId"
          ]
        }
      }
    },
    "User": {
      "name": "User",
      "columns": {
        "id": {
          "name": "id",
          "type": "varchar(36)",
          "primaryKey": false,
          "notNull": true,
          "autoincrement": false
        },
        "firstname": {
          "name": "firstname",
          "type": "varchar(255)",
          "primaryKey": false,
          "notNull": true,
          "autoincrement": false
        },
        "password": {
          "name": "password",
          "type": "varchar(255)",
          "primaryKey": false,
          "notNull": true,
          "autoincrement": false
        },
        "lastname": {
          "name": "lastname",
          "type": "varchar(255)",
          "primaryKey": false,
          "notNull": true,
          "autoincrement": false
        },
        "email": {
          "name": "email",
          "type": "varchar(255)",
          "primaryKey": false,
          "notNull": true,
          "autoincrement": false
        },
        "createdAt": {
          "name": "createdAt",
          "type": "datetime",
          "primaryKey": false,
          "notNull": true,
          "autoincrement": false
        },
        "updatedAt": {
          "name": "updatedAt",
          "type": "datetime",
          "primaryKey": false,
          "notNull": false,
          "autoincrement": false,
          "default": null
        }
      },
      "indexes": {
        "firstname": {
          "name": "firstname",
          "columns": [
            "firstname"
          ],
          "isUnique": false
        },
        "lastname": {
          "name": "lastname",
          "columns": [
            "lastname"
          ],
          "isUnique": false
        },
        "createdAt": {
          "name": "createdAt",
          "columns": [
            "createdAt"
          ],
          "isUnique": false
        },
        "updatedAt": {
          "name": "updatedAt",
          "columns": [
            "updatedAt"
          ],
          "isUnique": false
        }
      },
      "foreignKeys": {},
      "compositePrimaryKeys": {
        "User_id": {
          "name": "User_id",
          "columns": [
            "id"
          ]
        }
      },
      "uniqueConstraints": {
        "email": {
          "name": "email",
          "columns": [
            "email"
          ]
        }
      }
    }
  },
  "schemas": {},
  "_meta": {
    "schemas": {},
    "tables": {},
    "columns": {}
  }
}